nyxtools/__init__.py
nyxtools/_version.py
nyxtools/flyer.py
nyxtools/flyer_eiger2.py
nyxtools/handlers.py
nyxtools/isara_robot.py
nyxtools/nyx_raster_flyer.py
nyxtools/pilatus.py
nyxtools/robot.py
nyxtools/vector.py
nyxtools/tests/__init__.py
nyxtools/tests/conftest.py
nyxtools/tests/test_examples.py
nyxtools-0.0.13.dist-info/AUTHORS.rst
nyxtools-0.0.13.dist-info/LICENSE
nyxtools-0.0.13.dist-info/METADATA
nyxtools-0.0.13.dist-info/WHEEL
nyxtools-0.0.13.dist-info/entry_points.txt
nyxtools-0.0.13.dist-info/top_level.txt
nyxtools-0.0.13.dist-info/RECORD
