Metadata-Version: 2.1
Name: nyxtools
Version: 0.0.13
Summary: Common code for the NYX beamline at NSLS-II.
Home-page: https://github.com/JunAishima/nyxtools
Author: Brookhaven National Laboratory
Author-email: jaishima@bnl.gov
License: BSD (3-clause)
Classifier: Development Status :: 2 - Pre-Alpha
Classifier: Natural Language :: English
Classifier: Programming Language :: Python :: 3
Requires-Python: >=3.7
License-File: LICENSE
License-File: AUTHORS.rst
Requires-Dist: mxtools
Requires-Dist: area-detector-handlers
Requires-Dist: fabio
